{
  "மேஷம்": "வணிகத்தில் புதிய வாய்ப்புகள் தோன்றும். உறவுகளில் நெருக்கடியான சூழ்நிலைகளுக்கு தீர்வு காண முயற்சி செய்யுங்கள். உடல் சக்தி அதிகரிக்கும், ஆனால் மேன்மேலும் கவனம் தேவை.",
  "ரிஷபம்": "பணியிடத்தில் தாமதங்கள் ஏற்படலாம், அதனால் பொறுமை முக்கியம். குடும்ப உறவுகள் பலன் தரும் நேரம், சிந்தித்து செயல்படுங்கள். நிதி மேலாண்மையில் கவனம் செலுத்த வேண்டிய நாள்.",
  "மிதுனம்": "கல்வி மற்றும் பயிற்சியில் விருத்தி காண்பீர்கள். சந்தேகங்களைத் தெளிவாக்கி, உறுதியாக முடிவெடுக்க வேண்டும். பொருளாதாரத்தில் சிறிய முதலீடு நல்ல பலன்களை தரும்.",
  "கடகம்": "உறவுகளில் புது தொடக்கம் ஏற்படும், மன உறவு மேம்படும். வேலைப்பளு அதிகரிக்கும், ஆனால் மன அழுத்தம் குறையும். ஆரோக்கியத்தை மேம்படுத்த சிறந்த நாள்.",
  "சிம்மம்": "திறமைகளை வெளிப்படுத்தும் சந்தர்ப்பம் உள்ளது. தொழிலில் போட்டி நிலை உயரும், அதனால் செயல்திறன் முக்கியம். குடும்ப பிரச்சனைகள் உங்களை சிந்திக்க வைக்கும்.",
  "கன்னி": "தொழில் தொடர்பான முக்கிய முடிவுகள் எடுக்கப்படும். நிதி நிலை வலுவாகும், செலவுகளை கட்டுப்படுத்த வேண்டும். மனஅழுத்தம் குறைந்து, உறவுகள் உறுதியடையும்.",
  "துலாம்": "உறவுகளில் புதிய மாற்றங்கள் ஏற்படும், உறுதி வைக்க முயற்சி செய்யுங்கள். பணியில் புதிய சவால்கள் எதிர்கொள்ளப்படலாம். உடல் நலம் சிறப்பாக இருக்கும்.",
  "விருச்சிகம்": "திட்டங்களில் தடை ஏற்பட்டாலும், அதனை சமாளித்து முன்னேற வேண்டும். நிதி மேலாண்மையில் புதிய யோசனைகள் பயனுள்ளதாக இருக்கும். உறவு நிலைகளில் உணர்ச்சி மேலோட்டம் காணப்படும்.",
  "தனுசு": "பணியிடத்தில் விருப்பமான முன்னேற்றம் இருக்கும். குடும்ப உறவுகளில் சிக்கல்கள் ஏற்படலாம், அதனால் கவனமாக நடந்து கொள்ளுங்கள். நலம் பராமரிப்பில் சிறு கவனம் தேவை.",
  "மகரம்": "தொழிலில் புதிய வாய்ப்புகள் காணப்படும். நிதி நிலை உறுதியாகும், ஆனால் அதிக செலவுகளை தவிர்க்க வேண்டும். உறவுகளில் உண்மையான தொடர்புகள் வளர்ச்சி பெறும்.",
  "கும்பம்": "பணியாளர்களுடன் கருத்து வேறுபாடுகள் ஏற்படலாம், அதனால் விவாதங்களை தவிர்க்க முயற்சி செய்யுங்கள். ஆரோக்கியம் கவனிக்க வேண்டிய நாள். நிதி விஷயங்களில் நன்மைகள் கிடைக்கும்.",
  "மீனம்": "சிந்தனை திறன் மேம்படும், வேலைகளில் முன்னேற்றம் காணலாம். உறவுகளில் உணர்ச்சி பரிமாற்றம் அதிகரிக்கும், புதிய உறவுகள் தோன்றும். ஆரோக்கியம் சிறப்பாக இருக்கும், ஆனால் மன அழுத்தம் குறைக்க யோகமும் உதவும்."
}